{
  "movements": [
    {
      "ticker": "XNAS",
      "way": "BUY",
      "baseAmt": 2.916812,
      "quoteAmt": 125.01,
      "feeAmt": 0,
      "feeCur": "EUR",
      "date": "2025-06-02"
    },
    {
      "ticker": "XNAS",
      "way": "BUY",
      "baseAmt": 2.861066,
      "quoteAmt": 125.0,
      "feeAmt": 0,
      "feeCur": "EUR",
      "date": "2025-06-17"
    },
    {
      "ticker": "XNAS",
      "way": "BUY",
      "baseAmt": 3.38983,
      "quoteAmt": 150.0,
      "feeAmt": 0,
      "feeCur": "EUR",
      "date": "2025-07-02"
    },
    {
      "ticker": "BTC",
      "way": "BUY",
      "baseAmt": 0.00108271,
      "quoteAmt": 100.0,
      "feeAmt": 2.7e-06,
      "feeCur": "BTC",
      "date": "2025-07-07"
    },
    {
      "ticker": "XNAS",
      "way": "BUY",
      "baseAmt": 3.314917,
      "quoteAmt": 150.0,
      "feeAmt": 0,
      "feeCur": "EUR",
      "date": "2025-07-09"
    },
    {
      "ticker": "BTC",
      "way": "BUY",
      "baseAmt": 0.00321736,
      "quoteAmt": 300.0,
      "feeAmt": 1.094e-05,
      "feeCur": "BTC",
      "date": "2025-07-09"
    },
    {
      "ticker": "XNAS",
      "way": "BUY",
      "baseAmt": 0.266074,
      "quoteAmt": 12.29,
      "feeAmt": 0,
      "feeCur": "EUR",
      "date": "2025-08-04"
    },
    {
      "ticker": "XNAS",
      "way": "BUY",
      "baseAmt": 1.082485,
      "quoteAmt": 50.0,
      "feeAmt": 0,
      "feeCur": "EUR",
      "date": "2025-08-04"
    },
    {
      "ticker": "BTC",
      "way": "BUY",
      "baseAmt": 0.007992,
      "quoteAmt": 799.2,
      "feeAmt": 1.998e-05,
      "feeCur": "BTC",
      "date": "2025-08-08"
    },
    {
      "ticker": "XNAS",
      "way": "BUY",
      "baseAmt": 213.53833,
      "quoteAmt": 9998.93,
      "feeAmt": 1.0,
      "feeCur": "EUR",
      "date": "2025-08-08"
    },
    {
      "ticker": "BTC",
      "way": "BUY",
      "baseAmt": 0.00206862,
      "quoteAmt": 211.0,
      "feeAmt": 0.53,
      "feeCur": "EUR",
      "date": "2025-08-11"
    },
    {
      "ticker": "BTC",
      "way": "BUY",
      "baseAmt": 0.00479425,
      "quoteAmt": 501.0,
      "feeAmt": 1.199e-05,
      "feeCur": "BTC",
      "date": "2025-08-13"
    },
    {
      "ticker": "BTC",
      "way": "BUY",
      "baseAmt": 0.00201375,
      "quoteAmt": 205.0,
      "feeAmt": 0.51,
      "feeCur": "EUR",
      "date": "2025-08-14"
    },
    {
      "ticker": "BTC",
      "way": "BUY",
      "baseAmt": 0.00120434,
      "quoteAmt": 122.0,
      "feeAmt": 3.01e-06,
      "feeCur": "BTC",
      "date": "2025-08-14"
    },
    {
      "ticker": "BTC",
      "way": "BUY",
      "baseAmt": 0.00071709,
      "quoteAmt": 73.0,
      "feeAmt": 0.1825,
      "feeCur": "EUR",
      "date": "2025-08-15"
    },
    {
      "ticker": "XNAS",
      "way": "BUY",
      "baseAmt": 43.261951,
      "quoteAmt": 2000.0,
      "feeAmt": 1.0,
      "feeCur": "EUR",
      "date": "2025-08-21"
    },
    {
      "ticker": "BTC",
      "way": "BUY",
      "baseAmt": 0.00410256,
      "quoteAmt": 400.0,
      "feeAmt": 1.026e-05,
      "feeCur": "BTC",
      "date": "2025-08-21"
    },
    {
      "ticker": "BTC",
      "way": "BUY",
      "baseAmt": 0.00258821,
      "quoteAmt": 249.76,
      "feeAmt": 6.6e-07,
      "feeCur": "BTC",
      "date": "2025-08-27"
    },
    {
      "ticker": "BTC",
      "way": "BUY",
      "baseAmt": 0.01066279,
      "quoteAmt": 1000.17,
      "feeAmt": 2.666e-05,
      "feeCur": "BTC",
      "date": "2025-08-29"
    },
    {
      "ticker": "XNAS",
      "way": "BUY",
      "baseAmt": 0.090988,
      "quoteAmt": 4.19,
      "feeAmt": 0,
      "feeCur": "EUR",
      "date": "2025-09-03"
    },
    {
      "ticker": "XNAS",
      "way": "BUY",
      "baseAmt": 1.085776,
      "quoteAmt": 50.0,
      "feeAmt": 0,
      "feeCur": "EUR",
      "date": "2025-09-03"
    },
    {
      "ticker": "BTC",
      "way": "BUY",
      "baseAmt": 0.0002159828,
      "quoteAmt": 20.0,
      "feeAmt": 0,
      "feeCur": "EUR",
      "date": "2025-09-05"
    },
    {
      "ticker": "BTC",
      "way": "BUY",
      "baseAmt": 0.00051975,
      "quoteAmt": 50.0,
      "feeAmt": 0.125,
      "feeCur": "EUR",
      "date": "2025-09-22"
    },
    {
      "ticker": "BTC",
      "way": "SELL",
      "baseAmt": 1.5e-05,
      "quoteAmt": 1.42,
      "feeAmt": 0,
      "feeCur": "EUR",
      "date": "2025-09-23"
    },
    {
      "ticker": "IE00BYWYCC39",
      "way": "BUY",
      "baseAmt": 176.408636,
      "quoteAmt": 2664.53,
      "feeAmt": 1.0,
      "feeCur": "EUR",
      "date": "2025-09-29"
    },
    {
      "ticker": "BTC",
      "way": "BUY",
      "baseAmt": 0.00159915,
      "quoteAmt": 150.0,
      "feeAmt": 0.375,
      "feeCur": "EUR",
      "date": "2025-09-26"
    },
    {
      "ticker": "VVSM",
      "way": "BUY",
      "baseAmt": 4.119888,
      "quoteAmt": 200.0,
      "feeAmt": 0,
      "feeCur": "EUR",
      "date": "2025-10-02"
    },
    {
      "ticker": "VVSM",
      "way": "BUY",
      "baseAmt": 3.934684,
      "quoteAmt": 200.0,
      "feeAmt": 0,
      "feeCur": "EUR",
      "date": "2025-10-09"
    },
    {
      "ticker": "BTC",
      "way": "BUY",
      "baseAmt": 0.00050506,
      "quoteAmt": 50.0,
      "feeAmt": 0.125,
      "feeCur": "EUR",
      "date": "2025-10-10"
    },
    {
      "ticker": "VVSM",
      "way": "BUY",
      "baseAmt": 3.924646,
      "quoteAmt": 200.0,
      "feeAmt": 0,
      "feeCur": "EUR",
      "date": "2025-10-16"
    },
    {
      "ticker": "BTC",
      "way": "BUY",
      "baseAmt": 0.00053534,
      "quoteAmt": 50.0,
      "feeAmt": 0.125,
      "feeCur": "EUR",
      "date": "2025-10-30"
    },
    {
      "ticker": "VVSM",
      "way": "BUY",
      "baseAmt": 0.061671,
      "quoteAmt": 3.35,
      "feeAmt": 0,
      "feeCur": "EUR",
      "date": "2025-11-03"
    },
    {
      "ticker": "BTC",
      "way": "BUY",
      "baseAmt": 0.00054855,
      "quoteAmt": 50.0,
      "feeAmt": 0.125,
      "feeCur": "EUR",
      "date": "2025-11-04"
    },
    {
      "ticker": "VVSM",
      "way": "BUY",
      "baseAmt": 0.982511,
      "quoteAmt": 50.0,
      "feeAmt": 0,
      "feeCur": "EUR",
      "date": "2025-11-17"
    },
    {
      "ticker": "VVSM",
      "way": "BUY",
      "baseAmt": 0.982511,
      "quoteAmt": 50.0,
      "feeAmt": 0,
      "feeCur": "EUR",
      "date": "2025-12-02"
    },
    {
      "ticker": "VVSM",
      "way": "BUY",
      "baseAmt": 0.070691,
      "quoteAmt": 3.6,
      "feeAmt": 0,
      "feeCur": "EUR",
      "date": "2025-12-02"
    },
    {
      "ticker": "BTC",
      "way": "BUY",
      "baseAmt": 0.00062656,
      "quoteAmt": 50.0,
      "feeAmt": 0.125,
      "feeCur": "EUR",
      "date": "2025-12-03"
    },
    {
      "ticker": "BTC",
      "way": "BUY",
      "baseAmt": 0.00066667,
      "quoteAmt": 50.0,
      "feeAmt": 0.125,
      "feeCur": "EUR",
      "date": "2025-12-29"
    },
    {
      "ticker": "VVSM",
      "way": "BUY",
      "baseAmt": 0.114222,
      "quoteAmt": 6.16,
      "feeAmt": 0,
      "feeCur": "EUR",
      "date": "2026-01-02"
    },
    {
      "ticker": "VVSM",
      "way": "BUY",
      "baseAmt": 0.927127,
      "quoteAmt": 50.0,
      "feeAmt": 0,
      "feeCur": "EUR",
      "date": "2026-01-02"
    },
    {
      "ticker": "BTC",
      "way": "BUY",
      "baseAmt": 0.00066756,
      "quoteAmt": 50.0,
      "feeAmt": 0.125,
      "feeCur": "EUR",
      "date": "2026-01-21"
    },
    {
      "ticker": "BTC",
      "way": "BUY",
      "baseAmt": 0.00067385,
      "quoteAmt": 50.0,
      "feeAmt": 0.125,
      "feeCur": "EUR",
      "date": "2026-01-27"
    },
    {
      "ticker": "VVSM",
      "way": "BUY",
      "baseAmt": 1.680672,
      "quoteAmt": 100.0,
      "feeAmt": 0,
      "feeCur": "EUR",
      "date": "2026-02-02"
    },
    {
      "ticker": "VVSM",
      "way": "BUY",
      "baseAmt": 0.078151,
      "quoteAmt": 4.65,
      "feeAmt": 0,
      "feeCur": "EUR",
      "date": "2026-02-02"
    },
    {
      "ticker": "BTC",
      "way": "BUY",
      "baseAmt": 0.00090579,
      "quoteAmt": 50.0,
      "feeAmt": 0.125,
      "feeCur": "EUR",
      "date": "2026-02-05"
    },
    {
      "ticker": "VVSM",
      "way": "BUY",
      "baseAmt": 0.822639,
      "quoteAmt": 50.0,
      "feeAmt": 0,
      "feeCur": "EUR",
      "date": "2026-02-16"
    },
    {
      "ticker": "BTC",
      "way": "BUY",
      "baseAmt": 0.0001021,
      "quoteAmt": 6.0,
      "feeAmt": 0,
      "feeCur": "EUR",
      "date": "2026-02-17"
    },
    {
      "ticker": "BTC",
      "way": "BUY",
      "baseAmt": 0.00010088,
      "quoteAmt": 6.0,
      "feeAmt": 0,
      "feeCur": "EUR",
      "date": "2026-02-17"
    },
    {
      "ticker": "BTC",
      "way": "BUY",
      "baseAmt": 0.00121231,
      "quoteAmt": 69.3,
      "feeAmt": 0.35,
      "feeCur": "EUR",
      "date": "2026-02-17"
    },
    {
      "ticker": "BTC",
      "way": "BUY",
      "baseAmt": 1.142e-05,
      "quoteAmt": 0.65,
      "feeAmt": 0.01,
      "feeCur": "EUR",
      "date": "2026-02-17"
    },
    {
      "ticker": "VVSM",
      "way": "BUY",
      "baseAmt": 0.051299,
      "quoteAmt": 3.06,
      "feeAmt": 0,
      "feeCur": "EUR",
      "date": "2026-03-02"
    },
    {
      "ticker": "VVSM",
      "way": "BUY",
      "baseAmt": 3.352891,
      "quoteAmt": 200.0,
      "feeAmt": 0,
      "feeCur": "EUR",
      "date": "2026-03-02"
    },
    {
      "ticker": "BTC",
      "way": "BUY",
      "baseAmt": 9.813e-05,
      "quoteAmt": 6.0,
      "feeAmt": 0,
      "feeCur": "EUR",
      "date": "2026-03-06"
    },
    {
      "ticker": "BTC",
      "way": "BUY",
      "baseAmt": 0.00057179,
      "quoteAmt": 33.65,
      "feeAmt": 0,
      "feeCur": "EUR",
      "date": "2026-03-06"
    },
    {
      "ticker": "BTC",
      "way": "BUY",
      "baseAmt": 0.00010235,
      "quoteAmt": 6.0,
      "feeAmt": 0,
      "feeCur": "EUR",
      "date": "2026-03-09"
    },
    {
      "ticker": "BTC",
      "way": "BUY",
      "baseAmt": 0.00040455,
      "quoteAmt": 23.99,
      "feeAmt": 0.12,
      "feeCur": "EUR",
      "date": "2026-03-09"
    },
    {
      "ticker": "BTC",
      "way": "BUY",
      "baseAmt": 0.00032672,
      "quoteAmt": 20.0,
      "feeAmt": 0,
      "feeCur": "EUR",
      "date": "2026-03-26"
    },
    {
      "ticker": "BTC",
      "way": "BUY",
      "baseAmt": 0.00128656,
      "quoteAmt": 78.99,
      "feeAmt": 0.39,
      "feeCur": "EUR",
      "date": "2026-03-26"
    },
    {
      "ticker": "BTC",
      "way": "BUY",
      "baseAmt": 0.0010147,
      "quoteAmt": 59.0,
      "feeAmt": 0.3,
      "feeCur": "EUR",
      "date": "2026-03-28"
    },
    {
      "ticker": "BTC",
      "way": "BUY",
      "baseAmt": 0.0003465,
      "quoteAmt": 20.0,
      "feeAmt": 0,
      "feeCur": "EUR",
      "date": "2026-03-28"
    },
    {
      "ticker": "VVSM",
      "way": "BUY",
      "baseAmt": 0.10616,
      "quoteAmt": 6.1,
      "feeAmt": 0,
      "feeCur": "EUR",
      "date": "2026-04-02"
    },
    {
      "ticker": "VVSM",
      "way": "BUY",
      "baseAmt": 3.480682,
      "quoteAmt": 200.0,
      "feeAmt": 0,
      "feeCur": "EUR",
      "date": "2026-04-02"
    }
  ],
  "updated": "2026-04-18T05:43:35.363674",
  "source": "google_sheets",
  "total_movements": 62
}